setup.cfg
setup.py
tomaat/__init__.py
tomaat.egg-info/PKG-INFO
tomaat.egg-info/SOURCES.txt
tomaat.egg-info/dependency_links.txt
tomaat.egg-info/requires.txt
tomaat.egg-info/top_level.txt
tomaat/announcer/__init__.py
tomaat/announcer/discovery_admin.py
tomaat/announcer/discovery_service.py
tomaat/client/__init__.py
tomaat/examples/__init__.py
tomaat/examples/pytorch.py
tomaat/examples/tensorflow.py
tomaat/extras/__init__.py
tomaat/extras/niftynet.py
tomaat/extras/transforms.py
tomaat/extras/utils.py
tomaat/frameworks/__init__.py
tomaat/frameworks/pytorch.py
tomaat/frameworks/tf.py
tomaat/server/__init__.py
tomaat/server/service.py