Metadata-Version: 1.0
Name: tomaat
Version: 0.1.5
Summary: TOMAAT SERVER SIDE
Home-page: https://github.com/fmilletari/tomaat
Author: Fausto Milletari
Author-email: tomaat.segmentation@gmail.com
License: UNKNOWN
Platform: UNKNOWN
